[{"last_name":"Glenn","uuid":"454e0990-eb76-4fc5-9c36-2120a5d086e0","schema":"faculty","name":"Sarah Glenn","path":"/people/glenn-sarah"},{"last_name":"Moore","uuid":"a2c13034-c9a5-4acc-8a16-0519d915389f","schema":"student","name":"Clarence Moore","majors":[{"title":"Biochemistry"}],"graduation_year":2026,"hometown":"Baltimore, MD","path":"/people/moore-clarence"},{"last_name":"Lastname","uuid":"adfasf","schema":"student","name":"Firstname Lastname","majors":[{"title":null}],"graduation_year":"2027","hometown":"Brooklyn, NY","path":"/people/test-profile"}]